aio_alipay/AioAlipayClient.py
aio_alipay/AioWebUtils.py
aio_alipay/__init__.py
aio_alipay_sdk_python-3.6.462.dist-info/LICENSE
aio_alipay_sdk_python-3.6.462.dist-info/METADATA
aio_alipay_sdk_python-3.6.462.dist-info/WHEEL
aio_alipay_sdk_python-3.6.462.dist-info/top_level.txt
aio_alipay_sdk_python-3.6.462.dist-info/RECORD
