Metadata-Version: 2.1
Name: aio-alipay-sdk-python
Version: 3.6.462
Summary: The official Aliyun SDK for Python.
Home-page: https://github.com/Pig-Tong/aio-alipay-sdk-python
Author: zhut96
Author-email: zhut96@outlook.com
License: Apache
Keywords: alipay,sdk,aio
Platform: any
Classifier: Intended Audience :: Developers
Classifier: License :: OSI Approved :: Apache Software License
Classifier: Programming Language :: Python
Classifier: Programming Language :: Python :: 2.6
Classifier: Programming Language :: Python :: 2.7
Classifier: Programming Language :: Python :: 3
Classifier: Programming Language :: Python :: 3.3
Classifier: Topic :: Software Development
License-File: LICENSE
Requires-Dist: aiohttp
Requires-Dist: alipay-sdk-python
